CHANGES.txt
LICENSE.txt
MANIFEST.in
README.txt
setup.py
src/zeam/__init__.py
src/zeam.jsontemplate.egg-info/PKG-INFO
src/zeam.jsontemplate.egg-info/SOURCES.txt
src/zeam.jsontemplate.egg-info/dependency_links.txt
src/zeam.jsontemplate.egg-info/entry_points.txt
src/zeam.jsontemplate.egg-info/namespace_packages.txt
src/zeam.jsontemplate.egg-info/not-zip-safe
src/zeam.jsontemplate.egg-info/requires.txt
src/zeam.jsontemplate.egg-info/top_level.txt
src/zeam/jsontemplate/__init__.py
src/zeam/jsontemplate/test_jsontemplate.txt
src/zeam/jsontemplate/resources/README.txt
src/zeam/jsontemplate/resources/json-template.js