Metadata-Version: 1.0
Name: zeam.jsontemplate
Version: 0.1
Summary: Fanstatic packaging of json template
Home-page: UNKNOWN
Author: Fanstatic Developers
Author-email: fanstatic@googlegroups.com
License: BSD
Keywords: fanstatic jsontemplate
Platform: UNKNOWN
